[
  {
    "@id": "https://reeco-framework.github.io/ecosystem/entity/polifonia-project",
    "@type": [
      "https://schema.org/Project"
    ]
  },
  {
    "@id": "https://reeco-framework.github.io/ecosystem/entity/BELLS",
    "@type": [
      "http://purl.org/cerif/frapo/Investigation"
    ]
  },
  {
    "@id": "https://reeco-framework.github.io/ecosystem/entity/Patrizia",
    "@type": [
      "http://purl.org/cerif/frapo/MaterialOutput",
      "https://reeco-framework.github.io/ecosystem/entity/Persona"
    ],
    "https://schema.org/abstract": [
      {
        "@language": "en",
        "@value": "Ethnoanthropologist and Officer at the Italian Ministry of Culture"
      }
    ],
    "https://schema.org/identifier": [
      {
        "@value": "Patrizia"
      }
    ],
    "https://schema.org/isBasedOn": [
      {
        "@value": "Ethnoanthropologist and Officer at the Italian Ministry of Culture"
      },
      {
        "@value": "Patrizia#1_IdentificationOfIntangibleElements"
      }
    ],
    "https://schema.org/isPartOf": [
      {
        "@id": "https://reeco-framework.github.io/ecosystem/entity/polifonia-project"
      },
      {
        "@id": "https://reeco-framework.github.io/ecosystem/entity/BELLS"
      }
    ],
    "https://schema.org/license": [
      {
        "@value": "CC-BY_v4"
      }
    ],
    "https://schema.org/title": [
      {
        "@language": "en",
        "@value": "Patrizia"
      }
    ]
  }
]