[
  {
    "@id": "https://reeco-framework.github.io/ecosystem/entity/Jorge",
    "@type": [
      "http://purl.org/cerif/frapo/MaterialOutput",
      "https://reeco-framework.github.io/ecosystem/entity/Persona"
    ],
    "https://schema.org/abstract": [
      {
        "@language": "en",
        "@value": "Jorge is managing a library of music scores, and is responsible for the sub-part of the library catalog which is already digitized."
      }
    ],
    "https://schema.org/identifier": [
      {
        "@value": "Jorge"
      }
    ],
    "https://schema.org/isBasedOn": [
      {
        "@value": "Jorge is managing a library of music scores, and is responsible for the sub-part of the library catalog which is already digitized."
      },
      {
        "@value": "Jorge#1_OrganizeMyLibrary"
      },
      {
        "@value": "Jorge#3_DynamicExploration"
      },
      {
        "@value": "Jorge#4_LinkToSources"
      },
      {
        "@value": "Jorge#2_FindSimilarScores"
      }
    ],
    "https://schema.org/isPartOf": [
      {
        "@id": "https://reeco-framework.github.io/ecosystem/entity/polifonia-project"
      },
      {
        "@id": "https://reeco-framework.github.io/ecosystem/entity/FACETS"
      }
    ],
    "https://schema.org/title": [
      {
        "@language": "en",
        "@value": "Jorge"
      }
    ]
  },
  {
    "@id": "https://reeco-framework.github.io/ecosystem/entity/polifonia-project",
    "@type": [
      "https://schema.org/Project"
    ]
  },
  {
    "@id": "https://reeco-framework.github.io/ecosystem/entity/FACETS",
    "@type": [
      "http://purl.org/cerif/frapo/Investigation"
    ]
  }
]