{
    "@graph": [
        {
            "@id": "xyz:polifonia-project",
            "@type": "schema:Project"
        },
        {
            "@id": "xyz:WP3",
            "@type": "fabio:WorkPackage"
        },
        {
            "@id": "xyz:P2KG-Pipeline",
            "@type": [
                "xyz:Software",
                "frapo:MaterialOutput"
            ],
            "schema:contributor": [
                "Abdul Shahid <https://github.com/ashahidkhattak>",
                "Danny Diamond <https://github.com/danDiamo>",
                "James McDermott <https://github.com/jmmcd>"
            ],
            "schema:isPartOf": [
                {
                    "@id": "xyz:polifonia-project"
                },
                {
                    "@id": "xyz:WP3"
                }
            ],
            "schema:workExample": "https://projects.dharc.unibo.it/melody/fonn/statistics_on_the_session_annotated_subset_and_meertens_tune_collections_mtcann_pattern_kg",
            "schema:creditText": "This project has received funding from the European Union’s Horizon 2020 research and innovation programme under grant agreement N. 101004746",
            "schema:abstract": {
                "@language": "en",
                "@value": "This code takes the patterns generated by the FoNN tool in the form of pickle file and then creates knowledge graph of all the patterns found"
            },
            "schema:identifier": "P2KG-Pipeline",
            "schema:isBasedOn": "This code takes the patterns generated by the FoNN tool in the form of pickle file and then creates knowledge graph of all the patterns found",
            "schema:title": {
                "@language": "en",
                "@value": "P2KG - Pattern to Knowledge Graph JAMS Pipeline"
            }
        }
    ],
    "@context": {
        "schema": "https://schema.org/",
        "fx": "http://sparql.xyz/facade-x/ns/",
        "rdf": "http://www.w3.org/1999/02/22-rdf-syntax-ns#",
        "frapo": "http://purl.org/cerif/frapo/",
        "fabio": "http://purl.org/spar/fabio/",
        "xyz": "http://sparql.xyz/facade-x/data/",
        "xsd": "http://www.w3.org/2001/XMLSchema#",
        "rdfs": "http://www.w3.org/2000/01/rdf-schema#"
    }
}
